sklearn_minisom.py
sklearn_minisom-0.0.3.dist-info/LICENSE
sklearn_minisom-0.0.3.dist-info/METADATA
sklearn_minisom-0.0.3.dist-info/WHEEL
sklearn_minisom-0.0.3.dist-info/top_level.txt
sklearn_minisom-0.0.3.dist-info/RECORD
