Metadata-Version: 2.1
Name: sklearn_minisom
Version: 0.0.3
Summary: MiniSom library wrapper for seamless integration with SciKit-learn library.
Author-email: Jakub Kołodziej <jakvb.kolodziej@gmail.com>
Project-URL: Homepage, https://github.com/koloiyolo/sklearn_minisom/
Project-URL: Issues, https://github.com/koloiyolo/sklearn_minisom/issues
Classifier: Programming Language :: Python :: 3
Classifier: License :: OSI Approved :: MIT License
Classifier: Operating System :: OS Independent
Classifier: Topic :: Scientific/Engineering :: Artificial Intelligence
Requires-Python: >=3.8
License-File: LICENSE
Requires-Dist: scikit-learn
Requires-Dist: minisom>=2.3.3
Requires-Dist: numpy
Requires-Dist: scipy
